[
    {
        "person": {
            "name": "Jóna Albertsdóttir",
            "status": "",
            "unmarried": false,
            "birth": {
                "original_string": "F. 8/6 1883 á Svaði.",
                "date": "1883-06-08",
                "location": "Svaði"
            },
            "death": {
                "original_string": "D. 27/10 1892, 9 ára.",
                "date": "1892-10-27",
                "location": "",
                "note_ref": 1
            },
            "names": [
                "Jóna",
                "Albertsdóttir"
            ],
            "firstName": "Jóna",
            "lastName": "Albertsdóttir"
        },
        "spouse": [],
        "spouse_original_string": "",
        "parents": [
            {
                "name": "Guðmundur Albert Hallgrímsson",
                "note": "",
                "names": [
                    "Guðmundur",
                    "Albert",
                    "Hallgrímsson"
                ],
                "firstName": "Guðmundur",
                "lastName": "Hallgrímsson"
            },
            {
                "name": "María Kr. Benediktsdóttir",
                "note": "",
                "names": [
                    "María",
                    "Kr.",
                    "Benediktsdóttir"
                ],
                "firstName": "María",
                "lastName": "Benediktsdóttir"
            }
        ],
        "parents_original_string": "Guðmundur Albert Hallgrímsson og María Kr. Benediktsd.",
        "residence_history": [
            {
                "year": "1883",
                "original_string": "F. 8/6 1883 á Svaði.",
                "age": 0,
                "status": "Fæðingarstaður",
                "location": "Svaði"
            },
            {
                "original_string": "Hjá for. á Svaði (á 1.) 1883-1887.",
                "year": "1883-1887",
                "age": null,
                "status": "Hjá for.",
                "location": "Svaði",
                "note": "á 1."
            },
            {
                "original_string": "Hjá for. á Litla-Svaði ... 1888-1891.",
                "year": "1888-1891",
                "age": null,
                "status": "Hjá for.",
                "location": "Litla-Svaði",
                "note": ""
            }
        ],
        "notes": {
            "1": "Barn frá Svaði."
        },
        "pageUrl": "https://issuu.com/heradsskjalasafnthingeyinga/docs/b_k_42/8",
        "bok": "bok42",
        "number": 8,
        "_id": "bok42-8"
    },
    {
        "person": {
            "name": "Jóna Andrésdóttir",
            "status": "",
            "unmarried": false,
            "birth": {
                "original_string": "F. 8/7 1840 á Syðri-Skál.",
                "date": "1840-07-08",
                "location": "Syðri-Leikskálaá",
                "location_obj": {
                    "id": 25662,
                    "name": "Syðri-Leikskálaá",
                    "lat": "65.903681",
                    "lng": "-17.569109",
                    "location_type": {
                        "id": 1,
                        "name": "Heimilisfang"
                    },
                    "parent": [
                        {
                            "name": "Kaldakinn",
                            "id": 16594
                        },
                        {
                            "name": "Suður-Þingeyjarsýsla",
                            "id": 1003354
                        },
                        {
                            "name": "Ísland",
                            "id": 16573
                        }
                    ]
                }
            },
            "death": {
                "original_string": "D. 25/3 1904",
                "date": "1904-03-25",
                "location": ""
            },
            "names": [
                "Jóna",
                "Andrésdóttir"
            ],
            "firstName": "Jóna",
            "lastName": "Andrésdóttir"
        },
        "spouse": [
            {
                "name": "Jónas Sigurðsson",
                "date": "1860-10-30",
                "status": "",
                "names": [
                    "Jónas",
                    "Sigurðsson"
                ],
                "firstName": "Jónas",
                "lastName": "Sigurðsson"
            }
        ],
        "spouse_original_string": "Jónas Sigurðsson (g. 30/10 1860).",
        "parents": [
            {
                "name": "H. Ólafsson",
                "note": "",
                "names": [
                    "H.",
                    "Ólafsson"
                ],
                "firstName": "H.",
                "lastName": "Ólafsson"
            },
            {
                "name": "Sesselja Jónsdóttir",
                "note": "hj. á Syðri-Skál",
                "names": [
                    "Sesselja",
                    "Jónsdóttir"
                ],
                "firstName": "Sesselja",
                "lastName": "Jónsdóttir"
            }
        ],
        "parents_original_string": "H. Ólafsson og Sesselja Jónsdóttir, hj. á Syðri-Skál.",
        "residence_history": [
            {
                "year": "1840",
                "original_string": "F. 8/7 1840 á Syðri-Skál.",
                "age": 0,
                "status": "Fæðingarstaður",
                "location": "Syðri-Leikskálaá",
                "location_obj": {
                    "id": 25662,
                    "name": "Syðri-Leikskálaá",
                    "lat": "65.903681",
                    "lng": "-17.569109",
                    "location_type": {
                        "id": 1,
                        "name": "Heimilisfang"
                    },
                    "parent": [
                        {
                            "name": "Kaldakinn",
                            "id": 16594
                        },
                        {
                            "name": "Suður-Þingeyjarsýsla",
                            "id": 1003354
                        },
                        {
                            "name": "Ísland",
                            "id": 16573
                        }
                    ]
                }
            },
            {
                "original_string": "Hjá for. í Fagranesi 1846-1860 (7-20 ára)",
                "year": "1846-1860",
                "age": null,
                "status": "Hjá for.",
                "location": "Fagranesi",
                "note": "7-20 ára",
                "location_obj": {
                    "id": 25928,
                    "name": "Fagranes",
                    "lat": "65.805692",
                    "lng": "-17.415805",
                    "location_type": {
                        "id": 1,
                        "name": "Heimilisfang"
                    },
                    "parent": [
                        {
                            "name": "Reykjadalur",
                            "id": 16405
                        },
                        {
                            "name": "Suður-Þingeyjarsýsla",
                            "id": 1003354
                        },
                        {
                            "name": "Ísland",
                            "id": 16573
                        }
                    ]
                }
            },
            {
                "original_string": "Húsfr. í Fagranesi (22) 1861.",
                "year": "1861",
                "age": 22,
                "status": "Húsfr.",
                "location": "Fagranesi",
                "note": "",
                "location_obj": {
                    "id": 25928,
                    "name": "Fagranes",
                    "lat": "65.805692",
                    "lng": "-17.415805",
                    "location_type": {
                        "id": 1,
                        "name": "Heimilisfang"
                    },
                    "parent": [
                        {
                            "name": "Reykjadalur",
                            "id": 16405
                        },
                        {
                            "name": "Suður-Þingeyjarsýsla",
                            "id": 1003354
                        },
                        {
                            "name": "Ísland",
                            "id": 16573
                        }
                    ]
                }
            },
            {
                "original_string": "Húsfr. í Rauðuskriðu (23) 1862-1864.",
                "year": "1862-1864",
                "age": 23,
                "status": "Húsfr.",
                "location": "Rauðuskriðu",
                "note": "",
                "location_obj": {
                    "id": 24909,
                    "name": "Rauðaskriða",
                    "lat": "65.836736",
                    "lng": "-17.472869",
                    "location_type": {
                        "id": 1,
                        "name": "Heimilisfang"
                    },
                    "parent": [
                        {
                            "name": "Aðaldalur",
                            "id": 16498
                        },
                        {
                            "name": "Suður-Þingeyjarsýsla",
                            "id": 1003354
                        },
                        {
                            "name": "Ísland",
                            "id": 16573
                        }
                    ]
                }
            },
            {
                "original_string": "Húsfr. í Hraungerði (27) 1867-1877.",
                "year": "1867-1877",
                "age": 27,
                "status": "Húsfr.",
                "location": "Hraungerði",
                "note": ""
            },
            {
                "original_string": "Húsfr. í Hraun (37) 1878-1900-",
                "year": "1878-1900",
                "age": 37,
                "status": "Húsfr.",
                "location": "Hraun",
                "note": "",
                "location_obj": {
                    "id": 33784,
                    "name": "Hraun",
                    "lat": "65.839681",
                    "lng": "-17.353585",
                    "location_type": {
                        "id": 1,
                        "name": "Heimilisfang"
                    },
                    "parent": [
                        {
                            "name": "Aðaldalur",
                            "id": 16498
                        },
                        {
                            "name": "Suður-Þingeyjarsýsla",
                            "id": 1003354
                        },
                        {
                            "name": "Ísland",
                            "id": 16573
                        }
                    ]
                }
            }
        ],
        "notes": {},
        "pageUrl": "https://issuu.com/heradsskjalasafnthingeyinga/docs/b_k_42/9",
        "bok": "bok42",
        "number": 9,
        "_id": "bok42-9"
    },
    {
        "person": {
            "name": "Jóna Gísladóttir",
            "status": "",
            "unmarried": false,
            "birth": {
                "original_string": "F. um 1863.",
                "date": "1863",
                "location": ""
            },
            "death": {
                "original_string": "",
                "date": "",
                "location": ""
            },
            "names": [
                "Jóna",
                "Gísladóttir"
            ],
            "firstName": "Jóna",
            "lastName": "Gísladóttir"
        },
        "spouse": [],
        "spouse_original_string": "",
        "parents": [],
        "parents_original_string": "For. : ",
        "residence_history": [
            {
                "original_string": "Hjú á Stórutjörnum (25) 1888.",
                "year": "1888",
                "age": 25,
                "status": "Hjú",
                "location": "Stóru-Tjarnir",
                "note": "",
                "location_obj": {
                    "id": 15135,
                    "name": "Stóru-Tjarnir",
                    "lat": "65.7077204415",
                    "lng": "-17.7257537842",
                    "location_type": {
                        "id": 88,
                        "name": "Örnefni"
                    },
                    "parent": [
                        {
                            "name": "Suður-Þingeyjarsýsla",
                            "id": 1003354
                        },
                        {
                            "name": "Ísland",
                            "id": 16573
                        }
                    ]
                }
            }
        ],
        "notes": {},
        "pageUrl": "https://issuu.com/heradsskjalasafnthingeyinga/docs/b_k_42/10",
        "bok": "bok42",
        "number": 10,
        "_id": "bok42-10"
    },
    {
        "person": {
            "name": "Jóna Guðjónsdóttir",
            "status": "",
            "unmarried": false,
            "birth": {
                "original_string": "F. 5/6 1883 á Máná.",
                "date": "1883-06-05",
                "location": "Máná",
                "location_obj": {
                    "id": 13530,
                    "name": "Máná",
                    "lat": "66.196792",
                    "lng": "-17.105147",
                    "location_type": {
                        "id": 88,
                        "name": "Örnefni"
                    },
                    "parent": [
                        {
                            "name": "Suður-Þingeyjarsýsla",
                            "id": 1003354
                        },
                        {
                            "name": "Ísland",
                            "id": 16573
                        }
                    ]
                }
            },
            "death": {
                "original_string": "",
                "date": "",
                "location": ""
            },
            "names": [
                "Jóna",
                "Guðjónsdóttir"
            ],
            "firstName": "Jóna",
            "lastName": "Guðjónsdóttir"
        },
        "spouse": [],
        "spouse_original_string": "",
        "parents": [
            {
                "name": "G. Þorkelsson",
                "note": "",
                "names": [
                    "G.",
                    "Þorkelsson"
                ],
                "firstName": "G.",
                "lastName": "Þorkelsson"
            },
            {
                "name": "Guðrún Gísladóttir",
                "note": "",
                "names": [
                    "Guðrún",
                    "Gísladóttir"
                ],
                "firstName": "Guðrún",
                "lastName": "Gísladóttir"
            }
        ],
        "parents_original_string": "G. Þorkelsson og Guðrún Gísladóttir.",
        "residence_history": [
            {
                "year": "1883",
                "original_string": "F. 5/6 1883 á Máná.",
                "age": 0,
                "status": "Fæðingarstaður",
                "location": "Máná",
                "location_obj": {
                    "id": 13530,
                    "name": "Máná",
                    "lat": "66.196792",
                    "lng": "-17.105147",
                    "location_type": {
                        "id": 88,
                        "name": "Örnefni"
                    },
                    "parent": [
                        {
                            "name": "Suður-Þingeyjarsýsla",
                            "id": 1003354
                        },
                        {
                            "name": "Ísland",
                            "id": 16573
                        }
                    ]
                }
            },
            {
                "original_string": "Hjá móður á Máná (1. ári) 1883-1884.",
                "year": "1883-1884",
                "age": null,
                "status": "Hjá móður",
                "location": "Máná",
                "note": "1. ári",
                "location_obj": {
                    "id": 13530,
                    "name": "Máná",
                    "lat": "66.196792",
                    "lng": "-17.105147",
                    "location_type": {
                        "id": 88,
                        "name": "Örnefni"
                    },
                    "parent": [
                        {
                            "name": "Suður-Þingeyjarsýsla",
                            "id": 1003354
                        },
                        {
                            "name": "Ísland",
                            "id": 16573
                        }
                    ]
                }
            },
            {
                "original_string": "Hjá for. á Hofi (6) 1889-1899-",
                "year": "1889-1899",
                "age": 6,
                "status": "Hjá for.",
                "location": "Hofi",
                "note": ""
            }
        ],
        "notes": {},
        "pageUrl": "https://issuu.com/heradsskjalasafnthingeyinga/docs/b_k_42/11",
        "bok": "bok42",
        "number": 11,
        "_id": "bok42-11"
    },
    {
        "person": {
            "name": "Jóna Guðmundsdóttir",
            "status": "",
            "unmarried": false,
            "birth": {
                "original_string": "F. um 1878.",
                "date": "1878",
                "location": ""
            },
            "death": {
                "original_string": "",
                "date": "",
                "location": ""
            },
            "names": [
                "Jóna",
                "Guðmundsdóttir"
            ],
            "firstName": "Jóna",
            "lastName": "Guðmundsdóttir"
        },
        "spouse": [],
        "spouse_original_string": "",
        "parents": [],
        "parents_original_string": "For. : ",
        "residence_history": [
            {
                "original_string": "Hjú á Hálsi Fr. (19) 1897.",
                "year": "1897",
                "age": 19,
                "status": "Hjú",
                "location": "Hálsi Fn.",
                "note": "",
                "location_obj": {
                    "id": 33714,
                    "name": "Háls",
                    "lat": "65.738284",
                    "lng": "-17.869689",
                    "location_type": {
                        "id": 1,
                        "name": "Heimilisfang"
                    },
                    "parent": [
                        {
                            "name": "Fnjóskadalur",
                            "id": 16452
                        },
                        {
                            "name": "Suður-Þingeyjarsýsla",
                            "id": 1003354
                        },
                        {
                            "name": "Ísland",
                            "id": 16573
                        }
                    ]
                }
            }
        ],
        "notes": {},
        "pageUrl": "https://issuu.com/heradsskjalasafnthingeyinga/docs/b_k_42/12",
        "bok": "bok42",
        "number": 12,
        "_id": "bok42-12"
    },
    {
        "person": {
            "name": "Jóna Katrín Laxdal",
            "status": "Grímsd.",
            "unmarried": false,
            "birth": {
                "original_string": "F. 2/9 1895 á Húsavík.",
                "date": "1895-09-02",
                "location": "Húsavík",
                "location_obj": {
                    "id": 24308,
                    "name": "Húsavík",
                    "lat": "66.04465457784943",
                    "lng": "-17.34897332763694",
                    "location_type": {
                        "id": 2,
                        "name": "Sveitarfélag"
                    },
                    "parent": [
                        {
                            "name": "Suður-Þingeyjarsýsla",
                            "id": 1003354
                        },
                        {
                            "name": "Ísland",
                            "id": 16573
                        }
                    ]
                }
            },
            "death": {
                "original_string": "",
                "date": "",
                "location": ""
            },
            "names": [
                "Jóna",
                "Katrín",
                "Laxdal"
            ],
            "firstName": "Jóna",
            "lastName": "Laxdal"
        },
        "spouse": [],
        "spouse_original_string": "",
        "parents": [
            {
                "name": "Gr. J. Laxdal",
                "note": "",
                "names": [
                    "Gr.",
                    "J.",
                    "Laxdal"
                ],
                "firstName": "Gr.",
                "lastName": "Laxdal"
            },
            {
                "name": "Sveinbjörg Torfadóttir",
                "note": "",
                "names": [
                    "Sveinbjörg",
                    "Torfadóttir"
                ],
                "firstName": "Sveinbjörg",
                "lastName": "Torfadóttir"
            }
        ],
        "parents_original_string": "Gr. J. Laxdal og Sveinbjörg Torfadóttir.",
        "residence_history": [
            {
                "year": "1895",
                "original_string": "F. 2/9 1895 á Húsavík.",
                "age": 0,
                "status": "Fæðingarstaður",
                "location": "Húsavík",
                "location_obj": {
                    "id": 24308,
                    "name": "Húsavík",
                    "lat": "66.04465457784943",
                    "lng": "-17.34897332763694",
                    "location_type": {
                        "id": 2,
                        "name": "Sveitarfélag"
                    },
                    "parent": [
                        {
                            "name": "Suður-Þingeyjarsýsla",
                            "id": 1003354
                        },
                        {
                            "name": "Ísland",
                            "id": 16573
                        }
                    ]
                }
            },
            {
                "original_string": "Hjá for. í Læknishúsi (1. ári) 1895-1897.",
                "year": "1895-1897",
                "age": null,
                "status": "Hjá for.",
                "location": "Læknishúsi",
                "note": "1. ári"
            }
        ],
        "notes": {},
        "pageUrl": "https://issuu.com/heradsskjalasafnthingeyinga/docs/b_k_42/13",
        "bok": "bok42",
        "number": 13,
        "_id": "bok42-13"
    },
    {
        "person": {
            "name": "Jóna Sigurlaug Einarsdóttir",
            "status": "",
            "unmarried": false,
            "birth": {
                "original_string": "F. 10/12 1894 í Rauf.",
                "date": "1894-12-10",
                "location": "Rauf",
                "location_obj": {
                    "id": 13148,
                    "name": "Rauf",
                    "lat": null,
                    "lng": null,
                    "location_type": {
                        "id": 88,
                        "name": "Örnefni"
                    },
                    "parent": [
                        {
                            "name": "Tjörnes",
                            "id": 16460
                        },
                        {
                            "name": "Suður-Þingeyjarsýsla",
                            "id": 1003354
                        },
                        {
                            "name": "Ísland",
                            "id": 16573
                        }
                    ]
                }
            },
            "death": {
                "original_string": "",
                "date": "",
                "location": ""
            },
            "names": [
                "Jóna",
                "Sigurlaug",
                "Einarsdóttir"
            ],
            "firstName": "Jóna",
            "lastName": "Einarsdóttir"
        },
        "spouse": [
            {
                "name": "Ásgeir Kristjánsson",
                "date": "",
                "status": "",
                "names": [
                    "Ásgeir",
                    "Kristjánsson"
                ],
                "firstName": "Ásgeir",
                "lastName": "Kristjánsson"
            }
        ],
        "spouse_original_string": "Ásgeir Kristjánsson.",
        "parents": [
            {
                "name": "E. Jónsson",
                "note": "",
                "names": [
                    "E.",
                    "Jónsson"
                ],
                "firstName": "E.",
                "lastName": "Jónsson"
            },
            {
                "name": "Hólmfríður Þorgrímsdóttir",
                "note": "",
                "names": [
                    "Hólmfríður",
                    "Þorgrímsdóttir"
                ],
                "firstName": "Hólmfríður",
                "lastName": "Þorgrímsdóttir"
            }
        ],
        "parents_original_string": "E. Jónsson og Hólmfríður Þorgrímsdóttir.",
        "residence_history": [
            {
                "year": "1894",
                "original_string": "F. 10/12 1894 í Rauf.",
                "age": 0,
                "status": "Fæðingarstaður",
                "location": "Rauf",
                "location_obj": {
                    "id": 13148,
                    "name": "Rauf",
                    "lat": null,
                    "lng": null,
                    "location_type": {
                        "id": 88,
                        "name": "Örnefni"
                    },
                    "parent": [
                        {
                            "name": "Tjörnes",
                            "id": 16460
                        },
                        {
                            "name": "Suður-Þingeyjarsýsla",
                            "id": 1003354
                        },
                        {
                            "name": "Ísland",
                            "id": 16573
                        }
                    ]
                }
            },
            {
                "original_string": "Með for. í Rauf (1. ári) 1894 (Óskírt við...)",
                "year": "1894",
                "age": null,
                "status": "Með for.",
                "location": "Rauf",
                "note": "Óskírt við...",
                "location_obj": {
                    "id": 13148,
                    "name": "Rauf",
                    "lat": null,
                    "lng": null,
                    "location_type": {
                        "id": 88,
                        "name": "Örnefni"
                    },
                    "parent": [
                        {
                            "name": "Tjörnes",
                            "id": 16460
                        },
                        {
                            "name": "Suður-Þingeyjarsýsla",
                            "id": 1003354
                        },
                        {
                            "name": "Ísland",
                            "id": 16573
                        }
                    ]
                }
            },
            {
                "original_string": "Með for. á Hallbj.st. J. (1 árs) 1895-1896.",
                "year": "1895-1896",
                "age": null,
                "status": "Með for.",
                "location": "Hallbj.st. J.",
                "note": "1 árs"
            },
            {
                "original_string": "Með for. í Breiðuvík (3 ára) 1897.",
                "year": "1897",
                "age": null,
                "status": "Með for.",
                "location": "Breiðuvík",
                "note": "3 ára",
                "location_obj": {
                    "id": 16543,
                    "name": "Breiðavík",
                    "lat": "66.183688",
                    "lng": "-17.159323",
                    "location_type": {
                        "id": 1,
                        "name": "Heimilisfang"
                    },
                    "parent": [
                        {
                            "name": "Tjörnes",
                            "id": 16460
                        },
                        {
                            "name": "Suður-Þingeyjarsýsla",
                            "id": 1003354
                        },
                        {
                            "name": "Ísland",
                            "id": 16573
                        }
                    ]
                }
            },
            {
                "original_string": "Hjá for. á Borgarhóli (4 ára) 1898-1900.",
                "year": "1898-1900",
                "age": null,
                "status": "Hjá for.",
                "location": "Borgarhóli",
                "note": "4 ára"
            }
        ],
        "notes": {},
        "pageUrl": "https://issuu.com/heradsskjalasafnthingeyinga/docs/b_k_42/14",
        "bok": "bok42",
        "number": 14,
        "_id": "bok42-14"
    },
    {
        "person": {
            "name": "Jóna Jóakimsdóttir",
            "status": "",
            "unmarried": false,
            "birth": {
                "original_string": "F. um 1852.",
                "date": "1852",
                "location": ""
            },
            "death": {
                "original_string": "",
                "date": "",
                "location": ""
            },
            "names": [
                "Jóna",
                "Jóakimsdóttir"
            ],
            "firstName": "Jóna",
            "lastName": "Jóakimsdóttir"
        },
        "spouse": [],
        "spouse_original_string": "",
        "parents": [],
        "parents_original_string": "For. : ",
        "residence_history": [
            {
                "original_string": "Hjú á Sigurðarst. (17) 1869-1870.",
                "year": "1869-1870",
                "age": 17,
                "status": "Hjú",
                "location": "Sigurðarstaðir",
                "note": ""
            }
        ],
        "notes": {},
        "pageUrl": "https://issuu.com/heradsskjalasafnthingeyinga/docs/b_k_42/15",
        "bok": "bok42",
        "number": 15,
        "_id": "bok42-15"
    },
    {
        "person": {
            "name": "Jóna Jónasdóttir",
            "status": "",
            "unmarried": false,
            "birth": {
                "original_string": "F. 21/1 1870 í Yztuvík.",
                "date": "1870-01-21",
                "location": "Yztuvík",
                "location_obj": {
                    "id": 15849,
                    "name": "Ysta-Vík",
                    "lat": "65.821702",
                    "lng": "-18.052495",
                    "location_type": {
                        "id": 88,
                        "name": "Örnefni"
                    },
                    "parent": [
                        {
                            "name": "Suður-Þingeyjarsýsla",
                            "id": 1003354
                        },
                        {
                            "name": "Ísland",
                            "id": 16573
                        }
                    ]
                }
            },
            "death": {
                "original_string": "D. í Yztuvík 5/4 1902, 32 ára.",
                "date": "1902-04-05",
                "location": "Yztuvík",
                "note_ref": 1,
                "location_obj": {
                    "id": 15849,
                    "name": "Ysta-Vík",
                    "lat": "65.821702",
                    "lng": "-18.052495",
                    "location_type": {
                        "id": 88,
                        "name": "Örnefni"
                    },
                    "parent": [
                        {
                            "name": "Suður-Þingeyjarsýsla",
                            "id": 1003354
                        },
                        {
                            "name": "Ísland",
                            "id": 16573
                        }
                    ]
                }
            },
            "names": [
                "Jóna",
                "Jónasdóttir"
            ],
            "firstName": "Jóna",
            "lastName": "Jónasdóttir"
        },
        "spouse": [],
        "spouse_original_string": "",
        "parents": [
            {
                "name": "J. Jónsson",
                "note": "í Yztuvík",
                "names": [
                    "J.",
                    "Jónsson"
                ],
                "firstName": "J.",
                "lastName": "Jónsson"
            },
            {
                "name": "Hólmfríður Einarsdóttir",
                "note": "",
                "names": [
                    "Hólmfríður",
                    "Einarsdóttir"
                ],
                "firstName": "Hólmfríður",
                "lastName": "Einarsdóttir"
            }
        ],
        "parents_original_string": "J. Jónsson (í Yztuvík) og Hólmfríður Einarsdóttir.",
        "residence_history": [
            {
                "year": "1870",
                "original_string": "F. 21/1 1870 í Yztuvík.",
                "age": 0,
                "status": "Fæðingarstaður",
                "location": "Yztuvík",
                "location_obj": {
                    "id": 15849,
                    "name": "Ysta-Vík",
                    "lat": "65.821702",
                    "lng": "-18.052495",
                    "location_type": {
                        "id": 88,
                        "name": "Örnefni"
                    },
                    "parent": [
                        {
                            "name": "Suður-Þingeyjarsýsla",
                            "id": 1003354
                        },
                        {
                            "name": "Ísland",
                            "id": 16573
                        }
                    ]
                }
            },
            {
                "original_string": "Hjá for. í Yztuvík (1 árs) 1870-1873.",
                "year": "1870-1873",
                "age": null,
                "status": "Hjá for.",
                "location": "Yztuvík",
                "note": "1 árs",
                "location_obj": {
                    "id": 15849,
                    "name": "Ysta-Vík",
                    "lat": "65.821702",
                    "lng": "-18.052495",
                    "location_type": {
                        "id": 88,
                        "name": "Örnefni"
                    },
                    "parent": [
                        {
                            "name": "Suður-Þingeyjarsýsla",
                            "id": 1003354
                        },
                        {
                            "name": "Ísland",
                            "id": 16573
                        }
                    ]
                }
            },
            {
                "original_string": "Hjá for. í Sauðabrekkugerði (5) 1874.",
                "year": "1874",
                "age": 5,
                "status": "Hjá for.",
                "location": "Sauðabrekkugerði",
                "note": ""
            },
            {
                "original_string": "Hjá for. í Palsgerði (6) 1875-1878.",
                "year": "1875-1878",
                "age": 6,
                "status": "Hjá for.",
                "location": "Palsgerði",
                "note": ""
            },
            {
                "original_string": "Hjá for. í Yztuvík... 1879-1881-1887-1895.",
                "year": "1879-1895",
                "age": null,
                "status": "Hjá for.",
                "location": "Yztuvík",
                "note": "",
                "location_obj": {
                    "id": 15849,
                    "name": "Ysta-Vík",
                    "lat": "65.821702",
                    "lng": "-18.052495",
                    "location_type": {
                        "id": 88,
                        "name": "Örnefni"
                    },
                    "parent": [
                        {
                            "name": "Suður-Þingeyjarsýsla",
                            "id": 1003354
                        },
                        {
                            "name": "Ísland",
                            "id": 16573
                        }
                    ]
                }
            },
            {
                "year": "1902",
                "original_string": "D. í Yztuvík 5/4 1902, 32 ára.",
                "age": 0,
                "status": "Dánarstaður",
                "location": "Yztuvík",
                "location_obj": {
                    "id": 15849,
                    "name": "Ysta-Vík",
                    "lat": "65.821702",
                    "lng": "-18.052495",
                    "location_type": {
                        "id": 88,
                        "name": "Örnefni"
                    },
                    "parent": [
                        {
                            "name": "Suður-Þingeyjarsýsla",
                            "id": 1003354
                        },
                        {
                            "name": "Ísland",
                            "id": 16573
                        }
                    ]
                }
            }
        ],
        "notes": {
            "1": "Ung óg. stúlka í Yztuvík."
        },
        "pageUrl": "https://issuu.com/heradsskjalasafnthingeyinga/docs/b_k_42/16",
        "bok": "bok42",
        "number": 16,
        "_id": "bok42-16"
    },
    {
        "person": {
            "name": "Jóna Jónsdóttir",
            "status": "ósk.",
            "unmarried": true,
            "birth": {
                "original_string": "F. 18/9 1845 á Vatnsleysu.",
                "date": "1845-09-18",
                "location": "Vatnsleysu"
            },
            "death": {
                "original_string": "D. í Tungu F. 7/6 1894.",
                "date": "1894-06-07",
                "location": "Tungu F.",
                "note_ref": 1,
                "location_obj": {
                    "id": 25200,
                    "name": "Tunga",
                    "lat": "65.751172",
                    "lng": "-18.069293",
                    "location_type": {
                        "id": 1,
                        "name": "Heimilisfang"
                    },
                    "parent": [
                        {
                            "name": "Svalbarðsströnd",
                            "id": 25150
                        },
                        {
                            "name": "Suður-Þingeyjarsýsla",
                            "id": 1003354
                        },
                        {
                            "name": "Ísland",
                            "id": 16573
                        }
                    ]
                }
            },
            "names": [
                "Jóna",
                "Jónsdóttir"
            ],
            "firstName": "Jóna",
            "lastName": "Jónsdóttir"
        },
        "spouse": [],
        "spouse_original_string": "",
        "parents": [
            {
                "name": "J. Kristjánsson",
                "note": "",
                "names": [
                    "J.",
                    "Kristjánsson"
                ],
                "firstName": "J.",
                "lastName": "Kristjánsson"
            },
            {
                "name": "Jórunn Arngrímsdóttir",
                "note": "",
                "names": [
                    "Jórunn",
                    "Arngrímsdóttir"
                ],
                "firstName": "Jórunn",
                "lastName": "Arngrímsdóttir"
            }
        ],
        "parents_original_string": "J. Kristjánsson og Jórunn Arngrímsdóttir.",
        "residence_history": [
            {
                "year": "1845",
                "original_string": "F. 18/9 1845 á Vatnsleysu.",
                "age": 0,
                "status": "Fæðingarstaður",
                "location": "Vatnsleysu"
            },
            {
                "original_string": "Hjá for. á Vatnsleysu (1 árs) 1845.",
                "year": "1845",
                "age": null,
                "status": "Hjá for.",
                "location": "Vatnsleysu",
                "note": "1 árs"
            },
            {
                "original_string": "Hjá móður á sama bæ (2) 1846-1856.",
                "year": "1846-1856",
                "age": 2,
                "status": "Hjá móður",
                "location": "sama bæ",
                "note": ""
            },
            {
                "original_string": "Með bróður á Vatnsleysu (14) 1858-1859.",
                "year": "1858-1859",
                "age": 14,
                "status": "Með bróður",
                "location": "Vatnsleysu",
                "note": ""
            },
            {
                "original_string": "Hjú í Dali (16) 1860-1861.",
                "year": "1860-1861",
                "age": 16,
                "status": "Hjú",
                "location": "Dali",
                "note": ""
            },
            {
                "original_string": "Hjú á Vatnsenda (18) 1863.",
                "year": "1863",
                "age": 18,
                "status": "Hjú",
                "location": "Vatnsenda",
                "note": ""
            },
            {
                "original_string": "Hjú á Landamóti (19) 1864.",
                "year": "1864",
                "age": 19,
                "status": "Hjú",
                "location": "Landamóti",
                "note": "",
                "location_obj": {
                    "id": 16601,
                    "name": "Landamót",
                    "lat": "65.724831",
                    "lng": "-17.598935",
                    "location_type": {
                        "id": 1,
                        "name": "Heimilisfang"
                    },
                    "parent": [
                        {
                            "name": "Kaldakinn",
                            "id": 16594
                        },
                        {
                            "name": "Suður-Þingeyjarsýsla",
                            "id": 1003354
                        },
                        {
                            "name": "Ísland",
                            "id": 16573
                        }
                    ]
                }
            },
            {
                "original_string": "Hjú á Lundarbrekku (23) 1868-1869.",
                "year": "1868-1869",
                "age": 23,
                "status": "Hjú",
                "location": "Lundarbrekku",
                "note": "",
                "location_obj": {
                    "id": 16590,
                    "name": "Lundarbrekka",
                    "lat": "65.458496",
                    "lng": "-17.393892",
                    "location_type": {
                        "id": 1,
                        "name": "Heimilisfang"
                    },
                    "parent": [
                        {
                            "name": "Bárðardalur",
                            "id": 16538
                        },
                        {
                            "name": "Suður-Þingeyjarsýsla",
                            "id": 1003354
                        },
                        {
                            "name": "Ísland",
                            "id": 16573
                        }
                    ]
                }
            },
            {
                "original_string": "Hjú á Hvassastöðum (25) 1870.",
                "year": "1870",
                "age": 25,
                "status": "Hjú",
                "location": "Hvassastöðum",
                "note": ""
            },
            {
                "original_string": "Hjú á Veisu (26) 1871.",
                "year": "1871",
                "age": 26,
                "status": "Hjú",
                "location": "Veisu",
                "note": "",
                "location_obj": {
                    "id": 1001795,
                    "name": "Veisa",
                    "lat": "65.800414",
                    "lng": "-17.892034",
                    "location_type": {
                        "id": 1,
                        "name": "Heimilisfang"
                    },
                    "parent": [
                        {
                            "name": "Fnjóskadalur",
                            "id": 16452
                        },
                        {
                            "name": "Suður-Þingeyjarsýsla",
                            "id": 1003354
                        },
                        {
                            "name": "Ísland",
                            "id": 16573
                        }
                    ]
                }
            },
            {
                "original_string": "Hjú á Hallgilsstöðum (30) 1875.",
                "year": "1875",
                "age": 30,
                "status": "Hjú",
                "location": "Hallgilsstöðum",
                "note": "",
                "location_obj": {
                    "id": 16605,
                    "name": "Hallgilsstaðir",
                    "lat": "65.769241",
                    "lng": "-17.879596",
                    "location_type": {
                        "id": 1,
                        "name": "Heimilisfang"
                    },
                    "parent": [
                        {
                            "name": "Fnjóskadalur",
                            "id": 16452
                        },
                        {
                            "name": "Suður-Þingeyjarsýsla",
                            "id": 1003354
                        },
                        {
                            "name": "Ísland",
                            "id": 16573
                        }
                    ]
                }
            },
            {
                "original_string": "Hjákona B. á Hallgilsstöðum (31) 1877.",
                "year": "1877",
                "age": 31,
                "status": "Hjákona B.",
                "location": "Hallgilsstöðum",
                "note": "",
                "location_obj": {
                    "id": 16605,
                    "name": "Hallgilsstaðir",
                    "lat": "65.769241",
                    "lng": "-17.879596",
                    "location_type": {
                        "id": 1,
                        "name": "Heimilisfang"
                    },
                    "parent": [
                        {
                            "name": "Fnjóskadalur",
                            "id": 16452
                        },
                        {
                            "name": "Suður-Þingeyjarsýsla",
                            "id": 1003354
                        },
                        {
                            "name": "Ísland",
                            "id": 16573
                        }
                    ]
                }
            },
            {
                "original_string": "Hjú í Fjasatungu (39) 1884.",
                "year": "1884",
                "age": 39,
                "status": "Hjú",
                "location": "Fjasatungu",
                "note": ""
            },
            {
                "original_string": "Húsk. á Snæbjarnarst. (40) 1885-1886.",
                "year": "1885-1886",
                "age": 40,
                "status": "Húsk.",
                "location": "Snæbjarnarstaðir",
                "note": "",
                "location_obj": {
                    "id": 16608,
                    "name": "Snæbjarnarstaðir",
                    "lat": "65.548975",
                    "lng": "-17.68629",
                    "location_type": {
                        "id": 1,
                        "name": "Heimilisfang"
                    },
                    "parent": [
                        {
                            "name": "Fnjóskadalur",
                            "id": 16452
                        },
                        {
                            "name": "Suður-Þingeyjarsýsla",
                            "id": 1003354
                        },
                        {
                            "name": "Ísland",
                            "id": 16573
                        }
                    ]
                }
            },
            {
                "original_string": "Húsk. á Hálsi Fr. (42) 1887.",
                "year": "1887",
                "age": 42,
                "status": "Húsk.",
                "location": "Hálsi Fn.",
                "note": "",
                "location_obj": {
                    "id": 33714,
                    "name": "Háls",
                    "lat": "65.738284",
                    "lng": "-17.869689",
                    "location_type": {
                        "id": 1,
                        "name": "Heimilisfang"
                    },
                    "parent": [
                        {
                            "name": "Fnjóskadalur",
                            "id": 16452
                        },
                        {
                            "name": "Suður-Þingeyjarsýsla",
                            "id": 1003354
                        },
                        {
                            "name": "Ísland",
                            "id": 16573
                        }
                    ]
                }
            },
            {
                "original_string": "Hjú á Þorláksstöðum (44) 1889-",
                "year": "1889",
                "age": 44,
                "status": "Hjú",
                "location": "Sörlastöðum",
                "note": "",
                "location_obj": {
                    "id": 16609,
                    "name": "Sörlastaðir",
                    "lat": "65.557346",
                    "lng": "-17.673012",
                    "location_type": {
                        "id": 1,
                        "name": "Heimilisfang"
                    },
                    "parent": [
                        {
                            "name": "Fnjóskadalur",
                            "id": 16452
                        },
                        {
                            "name": "Suður-Þingeyjarsýsla",
                            "id": 1003354
                        },
                        {
                            "name": "Ísland",
                            "id": 16573
                        }
                    ]
                }
            },
            {
                "year": "1894",
                "original_string": "D. í Tungu F. 7/6 1894.",
                "age": 0,
                "status": "Dánarstaður",
                "location": "Tungu F.",
                "location_obj": {
                    "id": 25200,
                    "name": "Tunga",
                    "lat": "65.751172",
                    "lng": "-18.069293",
                    "location_type": {
                        "id": 1,
                        "name": "Heimilisfang"
                    },
                    "parent": [
                        {
                            "name": "Svalbarðsströnd",
                            "id": 25150
                        },
                        {
                            "name": "Suður-Þingeyjarsýsla",
                            "id": 1003354
                        },
                        {
                            "name": "Ísland",
                            "id": 16573
                        }
                    ]
                }
            }
        ],
        "notes": {
            "1": "Húsk, 48 ára. - Brjóstveiki. Dó úr inflúensu."
        },
        "pageUrl": "https://issuu.com/heradsskjalasafnthingeyinga/docs/b_k_42/17",
        "bok": "bok42",
        "number": 17,
        "_id": "bok42-17"
    },
    {
        "person": {
            "name": "Jóna Jónsdóttir",
            "status": "",
            "unmarried": false,
            "birth": {
                "original_string": "F. 20/9 1840 á Mýri.",
                "date": "1840-09-20",
                "location": "Mýri",
                "location_obj": {
                    "id": 24814,
                    "name": "Mýri",
                    "lat": "65.376773",
                    "lng": "-17.388316",
                    "location_type": {
                        "id": 1,
                        "name": "Heimilisfang"
                    },
                    "parent": [
                        {
                            "name": "Bárðardalur",
                            "id": 16538
                        },
                        {
                            "name": "Suður-Þingeyjarsýsla",
                            "id": 1003354
                        },
                        {
                            "name": "Ísland",
                            "id": 16573
                        }
                    ]
                }
            },
            "death": {
                "original_string": "",
                "date": "",
                "location": ""
            },
            "names": [
                "Jóna",
                "Jónsdóttir"
            ],
            "firstName": "Jóna",
            "lastName": "Jónsdóttir"
        },
        "spouse": [
            {
                "name": "Indriði Sigurðsson",
                "date": "1864-07-02",
                "status": "",
                "names": [
                    "Indriði",
                    "Sigurðsson"
                ],
                "firstName": "Indriði",
                "lastName": "Sigurðsson"
            }
        ],
        "spouse_original_string": "M. 2/7 1864 : Indriði Sigurðsson.",
        "parents": [
            {
                "name": "Jón Jónss. (Mýri)",
                "note": "",
                "names": [
                    "Jón",
                    "Jónss.",
                    "(Mýri)"
                ],
                "firstName": "Jón",
                "lastName": "(Mýri)"
            },
            {
                "name": "María Þorgrímsdóttir",
                "note": "",
                "names": [
                    "María",
                    "Þorgrímsdóttir"
                ],
                "firstName": "María",
                "lastName": "Þorgrímsdóttir"
            }
        ],
        "parents_original_string": "Jón Jónss. (Mýri) og María Þorgrímsdóttir.",
        "residence_history": [
            {
                "year": "1840",
                "original_string": "F. 20/9 1840 á Mýri.",
                "age": 0,
                "status": "Fæðingarstaður",
                "location": "Mýri",
                "location_obj": {
                    "id": 24814,
                    "name": "Mýri",
                    "lat": "65.376773",
                    "lng": "-17.388316",
                    "location_type": {
                        "id": 1,
                        "name": "Heimilisfang"
                    },
                    "parent": [
                        {
                            "name": "Bárðardalur",
                            "id": 16538
                        },
                        {
                            "name": "Suður-Þingeyjarsýsla",
                            "id": 1003354
                        },
                        {
                            "name": "Ísland",
                            "id": 16573
                        }
                    ]
                }
            },
            {
                "original_string": "Hjá móður á Bakka (5) 1844-45.",
                "year": "1844-1845",
                "age": 5,
                "status": "Hjá móður",
                "location": "Bakki",
                "note": "",
                "location_obj": {
                    "id": 12361,
                    "name": "Bakki",
                    "lat": "65.57006",
                    "lng": "-17.703681",
                    "location_type": {
                        "id": 1,
                        "name": "Heimilisfang"
                    },
                    "parent": [
                        {
                            "name": "Fnjóskadalur",
                            "id": 16452
                        },
                        {
                            "name": "Suður-Þingeyjarsýsla",
                            "id": 1003354
                        },
                        {
                            "name": "Ísland",
                            "id": 16573
                        }
                    ]
                }
            },
            {
                "original_string": "Hjá móður á Jarles t. B. (5) 1846.",
                "year": "1846",
                "age": 5,
                "status": "Hjá móður",
                "location": "Jarles t. B.",
                "note": ""
            },
            {
                "original_string": "Fósturb. á Mýri (8) 1849-1860.",
                "year": "1849-1860",
                "age": 8,
                "status": "Fósturb.",
                "location": "Mýri",
                "note": "",
                "location_obj": {
                    "id": 24814,
                    "name": "Mýri",
                    "lat": "65.376773",
                    "lng": "-17.388316",
                    "location_type": {
                        "id": 1,
                        "name": "Heimilisfang"
                    },
                    "parent": [
                        {
                            "name": "Bárðardalur",
                            "id": 16538
                        },
                        {
                            "name": "Suður-Þingeyjarsýsla",
                            "id": 1003354
                        },
                        {
                            "name": "Ísland",
                            "id": 16573
                        }
                    ]
                }
            },
            {
                "original_string": "Hjú á Mýri (21) 1861-1863.",
                "year": "1861-1863",
                "age": 21,
                "status": "Hjú",
                "location": "Mýri",
                "note": "",
                "location_obj": {
                    "id": 24814,
                    "name": "Mýri",
                    "lat": "65.376773",
                    "lng": "-17.388316",
                    "location_type": {
                        "id": 1,
                        "name": "Heimilisfang"
                    },
                    "parent": [
                        {
                            "name": "Bárðardalur",
                            "id": 16538
                        },
                        {
                            "name": "Suður-Þingeyjarsýsla",
                            "id": 1003354
                        },
                        {
                            "name": "Ísland",
                            "id": 16573
                        }
                    ]
                }
            },
            {
                "original_string": "Hjú á Fornastöðum (24) 1863-1864",
                "year": "1863-1864",
                "age": 24,
                "status": "Hjú",
                "location": "Fornastöðum",
                "note": "",
                "location_obj": {
                    "id": 16462,
                    "name": "Fornastaðir",
                    "lat": "65.7498465926765",
                    "lng": "-17.842139723144598",
                    "location_type": {
                        "id": 1,
                        "name": "Heimilisfang"
                    },
                    "parent": [
                        {
                            "name": "Fnjóskadalur",
                            "id": 16452
                        },
                        {
                            "name": "Suður-Þingeyjarsýsla",
                            "id": 1003354
                        },
                        {
                            "name": "Ísland",
                            "id": 16573
                        }
                    ]
                }
            },
            {
                "original_string": "Húsfr. á Veigursstöðum (28) 1867-1868",
                "year": "1867-1868",
                "age": 28,
                "status": "Húsfr.",
                "location": "Veigursstöðum",
                "note": ""
            },
            {
                "original_string": "Búst. á sama bæ (30) 1870.",
                "year": "1870",
                "age": 30,
                "status": "Búst.",
                "location": "sama bæ",
                "note": ""
            }
        ],
        "notes": {},
        "pageUrl": "https://issuu.com/heradsskjalasafnthingeyinga/docs/b_k_42/18",
        "bok": "bok42",
        "number": 18,
        "_id": "bok42-18"
    },
    {
        "person": {
            "name": "Jóna Jónsdóttir",
            "status": "",
            "unmarried": true,
            "birth": {
                "original_string": "F. 20/11 1830 í Mjóadal.",
                "date": "1830-11-20",
                "location": "Mjóadal"
            },
            "death": {
                "original_string": "D. 3/5 1899, 67 ára.",
                "date": "1899-05-03",
                "location": "",
                "note_ref": 1
            },
            "names": [
                "Jóna",
                "Jónsdóttir"
            ],
            "firstName": "Jóna",
            "lastName": "Jónsdóttir"
        },
        "spouse": [],
        "spouse_original_string": "",
        "parents": [
            {
                "name": "Jón Jónsson",
                "note": "Mjóadal",
                "names": [
                    "Jón",
                    "Jónsson"
                ],
                "firstName": "Jón",
                "lastName": "Jónsson"
            },
            {
                "name": "Aðalbjörg Davíðsdóttir",
                "note": "",
                "names": [
                    "Aðalbjörg",
                    "Davíðsdóttir"
                ],
                "firstName": "Aðalbjörg",
                "lastName": "Davíðsdóttir"
            }
        ],
        "parents_original_string": "Jón Jónsson (Mjóadal) og Aðalbjörg Davíðsdóttir.",
        "residence_history": [
            {
                "year": "1830",
                "original_string": "F. 20/11 1830 í Mjóadal.",
                "age": 0,
                "status": "Fæðingarstaður",
                "location": "Mjóadal"
            },
            {
                "original_string": "Hjá for. í Mjóadal (5) 1835-41. (þó ekki 1839).",
                "year": "1835-1841",
                "age": 5,
                "status": "Hjá for.",
                "location": "Mjóadal",
                "note": "þó ekki 1839"
            },
            {
                "original_string": "Hjá for. á Halldórsst. B. (7) 1839.",
                "year": "1839",
                "age": 7,
                "status": "Hjá for.",
                "location": "Halldórsstaðir B.",
                "note": "",
                "location_obj": {
                    "id": 16560,
                    "name": "Halldórsstaðir",
                    "lat": "65.449709",
                    "lng": "-17.410081",
                    "location_type": {
                        "id": 1,
                        "name": "Heimilisfang"
                    },
                    "parent": [
                        {
                            "name": "Bárðardalur",
                            "id": 16538
                        },
                        {
                            "name": "Suður-Þingeyjarsýsla",
                            "id": 1003354
                        },
                        {
                            "name": "Ísland",
                            "id": 16573
                        }
                    ]
                }
            },
            {
                "original_string": "Hjú á Halldórsst. B. (34) 1865-66.",
                "year": "1865-1866",
                "age": 34,
                "status": "Hjú",
                "location": "Halldórsstaðir B.",
                "note": "",
                "location_obj": {
                    "id": 16560,
                    "name": "Halldórsstaðir",
                    "lat": "65.449709",
                    "lng": "-17.410081",
                    "location_type": {
                        "id": 1,
                        "name": "Heimilisfang"
                    },
                    "parent": [
                        {
                            "name": "Bárðardalur",
                            "id": 16538
                        },
                        {
                            "name": "Suður-Þingeyjarsýsla",
                            "id": 1003354
                        },
                        {
                            "name": "Ísland",
                            "id": 16573
                        }
                    ]
                }
            },
            {
                "original_string": "Niðurs. á Jarles t. B. (43) 1874-79 (vitskert).",
                "year": "1874-1879",
                "age": 43,
                "status": "Niðurs.",
                "location": "Jarles t. B.",
                "note": "vitskert"
            }
        ],
        "notes": {
            "1": "Óg á Jarlsst. B. - Vitskert í 37 ár."
        },
        "pageUrl": "https://issuu.com/heradsskjalasafnthingeyinga/docs/b_k_42/19",
        "bok": "bok42",
        "number": 19,
        "_id": "bok42-19"
    },
    {
        "person": {
            "name": "Jóna Jónsdóttir",
            "status": "",
            "unmarried": false,
            "birth": {
                "original_string": "F. um 1880.",
                "date": "1880",
                "location": ""
            },
            "death": {
                "original_string": "",
                "date": "",
                "location": ""
            },
            "names": [
                "Jóna",
                "Jónsdóttir"
            ],
            "firstName": "Jóna",
            "lastName": "Jónsdóttir"
        },
        "spouse": [],
        "spouse_original_string": "",
        "parents": [
            {
                "name": "J. Jónsson",
                "note": "á Fjöllum",
                "names": [
                    "J.",
                    "Jónsson"
                ],
                "firstName": "J.",
                "lastName": "Jónsson"
            },
            {
                "name": "Anna Sigurðardóttir",
                "note": "",
                "names": [
                    "Anna",
                    "Sigurðardóttir"
                ],
                "firstName": "Anna",
                "lastName": "Sigurðardóttir"
            }
        ],
        "parents_original_string": "J. Jónsson (á Fjöllum) og Anna Sigurðardóttir.",
        "residence_history": [
            {
                "original_string": "Hjú í Sýslum. húsi (18 ára) 1898.",
                "year": "1898",
                "age": 18,
                "status": "Hjú",
                "location": "Sýslum. húsi",
                "note": ""
            }
        ],
        "notes": {},
        "pageUrl": "https://issuu.com/heradsskjalasafnthingeyinga/docs/b_k_42/20",
        "bok": "bok42",
        "number": 20,
        "_id": "bok42-20"
    },
    {
        "person": {
            "name": "Jóna Björg Sigurjónsdóttir",
            "status": "",
            "unmarried": false,
            "birth": {
                "original_string": "F. 5/9 1881 á Kvislarhóli.",
                "date": "1881-09-05",
                "location": "Kvislarhóli"
            },
            "death": {
                "original_string": "",
                "date": "",
                "location": ""
            },
            "names": [
                "Jóna",
                "Björg",
                "Sigurjónsdóttir"
            ],
            "firstName": "Jóna",
            "lastName": "Sigurjónsdóttir"
        },
        "spouse": [
            {
                "name": "Indriði Árnason",
                "date": "",
                "status": "",
                "names": [
                    "Indriði",
                    "Árnason"
                ],
                "firstName": "Indriði",
                "lastName": "Árnason"
            }
        ],
        "spouse_original_string": "Indriði Árnason.",
        "parents": [
            {
                "name": "S. Halldórsson",
                "note": "",
                "names": [
                    "S.",
                    "Halldórsson"
                ],
                "firstName": "S.",
                "lastName": "Halldórsson"
            },
            {
                "name": "Dóróthea Jensdóttir",
                "note": "",
                "names": [
                    "Dóróthea",
                    "Jensdóttir"
                ],
                "firstName": "Dóróthea",
                "lastName": "Jensdóttir"
            }
        ],
        "parents_original_string": "S. Halldórsson og Dóróthea Jensdóttir.",
        "residence_history": [
            {
                "year": "1881",
                "original_string": "F. 5/9 1881 á Kvislarhóli.",
                "age": 0,
                "status": "Fæðingarstaður",
                "location": "Kvislarhóli"
            },
            {
                "original_string": "Hjá for. á Kvislarhóli (1. ári) 1881-1886.",
                "year": "1881-1886",
                "age": null,
                "status": "Hjá for.",
                "location": "Kvislarhóli",
                "note": "1. ári"
            },
            {
                "original_string": "Hjá for. á Hallbj.st. J. (6 ára) 1887-1898.",
                "year": "1887-1898",
                "age": 6,
                "status": "Hjá for.",
                "location": "Hallbj.st. J.",
                "note": ""
            },
            {
                "original_string": "Hjú í Húsavík (18 ára) 1899-1900.",
                "year": "1899-1900",
                "age": 18,
                "status": "Hjú",
                "location": "Húsavík",
                "note": "",
                "location_obj": {
                    "id": 24308,
                    "name": "Húsavík",
                    "lat": "66.04465457784943",
                    "lng": "-17.34897332763694",
                    "location_type": {
                        "id": 2,
                        "name": "Sveitarfélag"
                    },
                    "parent": [
                        {
                            "name": "Suður-Þingeyjarsýsla",
                            "id": 1003354
                        },
                        {
                            "name": "Ísland",
                            "id": 16573
                        }
                    ]
                }
            }
        ],
        "notes": {},
        "pageUrl": "https://issuu.com/heradsskjalasafnthingeyinga/docs/b_k_42/21",
        "bok": "bok42",
        "number": 21,
        "_id": "bok42-21"
    },
    {
        "person": {
            "name": "Jóna Vilhjálmsdóttir",
            "status": "",
            "unmarried": false,
            "birth": {
                "original_string": "F. í Nesi, Grýt. 9/9 1881 í Nesi Grýt",
                "date": "1881-09-09",
                "location": "Nesi, Grýt",
                "location_obj": {
                    "id": 13945,
                    "name": "Nes",
                    "lat": "65.902255",
                    "lng": "-18.118468",
                    "location_type": {
                        "id": 1,
                        "name": "Heimilisfang"
                    },
                    "parent": [
                        {
                            "name": "Höfðahverfi",
                            "id": 24527
                        },
                        {
                            "name": "Suður-Þingeyjarsýsla",
                            "id": 1003354
                        },
                        {
                            "name": "Ísland",
                            "id": 16573
                        }
                    ]
                }
            },
            "death": {
                "original_string": "",
                "date": "",
                "location": ""
            },
            "names": [
                "Jóna",
                "Vilhjálmsdóttir"
            ],
            "firstName": "Jóna",
            "lastName": "Vilhjálmsdóttir"
        },
        "spouse": [],
        "spouse_original_string": "",
        "parents": [
            {
                "name": "Vilhjálmur Þorsteinsson",
                "note": "",
                "names": [
                    "Vilhjálmur",
                    "Þorsteinsson"
                ],
                "firstName": "Vilhjálmur",
                "lastName": "Þorsteinsson"
            },
            {
                "name": "Valgerður Einarsdóttir",
                "note": "",
                "names": [
                    "Valgerður",
                    "Einarsdóttir"
                ],
                "firstName": "Valgerður",
                "lastName": "Einarsdóttir"
            }
        ],
        "parents_original_string": "Vilhjálmur Þorsteinsson og Valgerður Einarsdóttir.",
        "residence_history": [
            {
                "year": "1881",
                "original_string": "F. í Nesi, Grýt. 9/9 1881 í Nesi Grýt",
                "age": 0,
                "status": "Fæðingarstaður",
                "location": "Nesi, Grýt",
                "location_obj": {
                    "id": 13945,
                    "name": "Nes",
                    "lat": "65.902255",
                    "lng": "-18.118468",
                    "location_type": {
                        "id": 1,
                        "name": "Heimilisfang"
                    },
                    "parent": [
                        {
                            "name": "Höfðahverfi",
                            "id": 24527
                        },
                        {
                            "name": "Suður-Þingeyjarsýsla",
                            "id": 1003354
                        },
                        {
                            "name": "Ísland",
                            "id": 16573
                        }
                    ]
                }
            },
            {
                "original_string": "Með for. í Nesi (á 1.) 1882-1887-1896.",
                "year": "1882-1896",
                "age": null,
                "status": "Með for.",
                "location": "Nesi",
                "note": "á 1.",
                "location_obj": {
                    "id": 13945,
                    "name": "Nes",
                    "lat": "65.902255",
                    "lng": "-18.118468",
                    "location_type": {
                        "id": 1,
                        "name": "Heimilisfang"
                    },
                    "parent": [
                        {
                            "name": "Höfðahverfi",
                            "id": 24527
                        },
                        {
                            "name": "Suður-Þingeyjarsýsla",
                            "id": 1003354
                        },
                        {
                            "name": "Ísland",
                            "id": 16573
                        }
                    ]
                }
            },
            {
                "original_string": "Hjá for. í Nesi ... 1898-1900-",
                "year": "1898-1900",
                "age": null,
                "status": "Hjá for.",
                "location": "Nesi",
                "note": "",
                "location_obj": {
                    "id": 13945,
                    "name": "Nes",
                    "lat": "65.902255",
                    "lng": "-18.118468",
                    "location_type": {
                        "id": 1,
                        "name": "Heimilisfang"
                    },
                    "parent": [
                        {
                            "name": "Höfðahverfi",
                            "id": 24527
                        },
                        {
                            "name": "Suður-Þingeyjarsýsla",
                            "id": 1003354
                        },
                        {
                            "name": "Ísland",
                            "id": 16573
                        }
                    ]
                }
            }
        ],
        "notes": {},
        "pageUrl": "https://issuu.com/heradsskjalasafnthingeyinga/docs/b_k_42/22",
        "bok": "bok42",
        "number": 22,
        "_id": "bok42-22"
    },
    {
        "person": {
            "name": "Jóna",
            "status": "",
            "unmarried": false,
            "birth": {
                "original_string": "F. um 1857.",
                "date": "1857",
                "location": ""
            },
            "death": {
                "original_string": "",
                "date": "",
                "location": ""
            },
            "names": [
                "Jóna"
            ],
            "firstName": "Jóna",
            "lastName": "Jóna"
        },
        "spouse": [],
        "spouse_original_string": "",
        "parents": [],
        "parents_original_string": "For. : ",
        "residence_history": [
            {
                "original_string": "Barn á Víðikeri (2) 1859.",
                "year": "1859",
                "age": 2,
                "status": "Barn",
                "location": "Víðikeri",
                "note": "",
                "location_obj": {
                    "id": 1000954,
                    "name": "Víðiker",
                    "lat": "65.418030",
                    "lng": "-17.281303",
                    "location_type": {
                        "id": 1,
                        "name": "Heimilisfang"
                    },
                    "parent": [
                        {
                            "name": "Bárðardalur",
                            "id": 16538
                        },
                        {
                            "name": "Suður-Þingeyjarsýsla",
                            "id": 1003354
                        },
                        {
                            "name": "Ísland",
                            "id": 16573
                        }
                    ]
                }
            }
        ],
        "notes": {},
        "pageUrl": "https://issuu.com/heradsskjalasafnthingeyinga/docs/b_k_42/23",
        "bok": "bok42",
        "number": 23,
        "_id": "bok42-23"
    },
    {
        "person": {
            "name": "Jónas",
            "status": "",
            "unmarried": false,
            "birth": {
                "original_string": "F. um ...",
                "date": "",
                "location": ""
            },
            "death": {
                "original_string": "",
                "date": "",
                "location": ""
            },
            "names": [
                "Jónas"
            ],
            "firstName": "Jónas",
            "lastName": "Jónas"
        },
        "spouse": [],
        "spouse_original_string": "",
        "parents": [],
        "parents_original_string": "For. : ...",
        "residence_history": [
            {
                "original_string": "Hjú á Uppibæ .. -1811-",
                "year": "1811",
                "age": null,
                "status": "Hjú",
                "location": "Uppibæ",
                "note": ""
            }
        ],
        "notes": {},
        "pageUrl": "https://issuu.com/heradsskjalasafnthingeyinga/docs/b_k_42/24",
        "bok": "bok42",
        "number": 24,
        "_id": "bok42-24"
    },
    {
        "person": {
            "name": "Jónas Albertsson",
            "status": "",
            "unmarried": false,
            "birth": {
                "original_string": "F. 3/5 1885 á Svaði.",
                "date": "1885-05-03",
                "location": "Svaði"
            },
            "death": {
                "original_string": "",
                "date": "",
                "location": ""
            },
            "names": [
                "Jónas",
                "Albertsson"
            ],
            "firstName": "Jónas",
            "lastName": "Albertsson"
        },
        "spouse": [],
        "spouse_original_string": "",
        "parents": [
            {
                "name": "Guðmundur Albert Hallgrímsson",
                "note": "",
                "names": [
                    "Guðmundur",
                    "Albert",
                    "Hallgrímsson"
                ],
                "firstName": "Guðmundur",
                "lastName": "Hallgrímsson"
            },
            {
                "name": "María Kr. Benediktsdóttir",
                "note": "",
                "names": [
                    "María",
                    "Kr.",
                    "Benediktsdóttir"
                ],
                "firstName": "María",
                "lastName": "Benediktsdóttir"
            }
        ],
        "parents_original_string": "Guðmundur Albert Hallgrímsson og María Kr. Benediktsd.",
        "residence_history": [
            {
                "year": "1885",
                "original_string": "F. 3/5 1885 á Svaði.",
                "age": 0,
                "status": "Fæðingarstaður",
                "location": "Svaði"
            },
            {
                "original_string": "Hjá for. á Svaði (1 árs) 1885-1887.",
                "year": "1885-1887",
                "age": null,
                "status": "Hjá for.",
                "location": "Svaði",
                "note": "1 árs"
            },
            {
                "original_string": "Lettadr. á Illugastöðum (9) 1894-1895.",
                "year": "1894-1895",
                "age": 9,
                "status": "Lettadr.",
                "location": "Illugastöðum",
                "note": "",
                "location_obj": {
                    "id": 16606,
                    "name": "Illugastaðir",
                    "lat": "65.620875",
                    "lng": "-17.816004",
                    "location_type": {
                        "id": 1,
                        "name": "Heimilisfang"
                    },
                    "parent": [
                        {
                            "name": "Fnjóskadalur",
                            "id": 16452
                        },
                        {
                            "name": "Suður-Þingeyjarsýsla",
                            "id": 1003354
                        },
                        {
                            "name": "Ísland",
                            "id": 16573
                        }
                    ]
                }
            },
            {
                "original_string": "Lettadr. í Hléskógum (14) 1899.",
                "year": "1899",
                "age": 14,
                "status": "Lettadr.",
                "location": "Hléskógum",
                "note": "",
                "location_obj": {
                    "id": 1004889,
                    "name": "Hléskógar",
                    "lat": "65.9266171247136",
                    "lng": "-18.094241195678933",
                    "location_type": {
                        "id": 1,
                        "name": "Heimilisfang"
                    },
                    "parent": [
                        {
                            "name": "Höfðahverfi",
                            "id": 24527
                        },
                        {
                            "name": "Suður-Þingeyjarsýsla",
                            "id": 1003354
                        },
                        {
                            "name": "Ísland",
                            "id": 16573
                        }
                    ]
                }
            }
        ],
        "notes": {},
        "pageUrl": "https://issuu.com/heradsskjalasafnthingeyinga/docs/b_k_42/25",
        "bok": "bok42",
        "number": 25,
        "_id": "bok42-25"
    },
    {
        "person": {
            "name": "Jónas Andrésson",
            "status": "",
            "unmarried": true,
            "birth": {
                "original_string": "F. á Þverá L., skírður 14/7 1770.",
                "date": "1770-07-14",
                "location": "Þverá L.",
                "location_obj": {
                    "id": 25899,
                    "name": "Þverá",
                    "lat": "65.730993",
                    "lng": "-17.244662",
                    "location_type": {
                        "id": 33,
                        "name": "Bær"
                    },
                    "parent": [
                        {
                            "name": "Laxárdalur",
                            "id": 24700
                        },
                        {
                            "name": "Suður-Þingeyjarsýsla",
                            "id": 1003354
                        },
                        {
                            "name": "Ísland",
                            "id": 16573
                        }
                    ]
                }
            },
            "death": {
                "original_string": "D. á Botni 20/7 1859.",
                "date": "1859-07-20",
                "location": "Botni",
                "note_ref": 1,
                "location_obj": {
                    "id": 25665,
                    "name": "Botn",
                    "lat": "66.151975",
                    "lng": "-18.142719",
                    "location_type": {
                        "id": 1,
                        "name": "Heimilisfang"
                    },
                    "parent": [
                        {
                            "name": "Þorgeirsfjörður",
                            "id": 25312
                        },
                        {
                            "name": "Suður-Þingeyjarsýsla",
                            "id": 1003354
                        },
                        {
                            "name": "Ísland",
                            "id": 16573
                        }
                    ]
                }
            },
            "names": [
                "Jónas",
                "Andrésson"
            ],
            "firstName": "Jónas",
            "lastName": "Andrésson"
        },
        "spouse": [],
        "spouse_original_string": "",
        "parents": [
            {
                "name": "Andrés Arngrímsson",
                "note": "",
                "names": [
                    "Andrés",
                    "Arngrímsson"
                ],
                "firstName": "Andrés",
                "lastName": "Arngrímsson"
            },
            {
                "name": "Björg Sugjaldsdóttir",
                "note": "",
                "names": [
                    "Björg",
                    "Sugjaldsdóttir"
                ],
                "firstName": "Björg",
                "lastName": "Sugjaldsdóttir"
            }
        ],
        "parents_original_string": "Andrés Arngrímsson og Björg Sugjaldsdóttir.",
        "residence_history": [
            {
                "year": "1770",
                "original_string": "F. á Þverá L., skírður 14/7 1770.",
                "age": 0,
                "status": "Fæðingarstaður",
                "location": "Þverá L.",
                "location_obj": {
                    "id": 25899,
                    "name": "Þverá",
                    "lat": "65.730993",
                    "lng": "-17.244662",
                    "location_type": {
                        "id": 33,
                        "name": "Bær"
                    },
                    "parent": [
                        {
                            "name": "Laxárdalur",
                            "id": 24700
                        },
                        {
                            "name": "Suður-Þingeyjarsýsla",
                            "id": 1003354
                        },
                        {
                            "name": "Ísland",
                            "id": 16573
                        }
                    ]
                }
            },
            {
                "original_string": "Hjú í Neðribæ (31) 1801-",
                "year": "1801",
                "age": 31,
                "status": "Hjú",
                "location": "Neðribæ",
                "note": ""
            },
            {
                "original_string": "Hússkarl á Sigríðarstöðum (60) 1829-38",
                "year": "1829-1838",
                "age": 60,
                "status": "Hússkarl",
                "location": "Sigríðarstöðum",
                "note": "",
                "location_obj": {
                    "id": 16619,
                    "name": "Sigríðarstaðir",
                    "lat": "65.724823",
                    "lng": "-17.777594",
                    "location_type": {
                        "id": 1,
                        "name": "Heimilisfang"
                    },
                    "parent": [
                        {
                            "name": "Ljósavatnsskarð",
                            "id": 24734
                        },
                        {
                            "name": "Suður-Þingeyjarsýsla",
                            "id": 1003354
                        },
                        {
                            "name": "Ísland",
                            "id": 16573
                        }
                    ]
                }
            },
            {
                "year": "1859",
                "original_string": "D. á Botni 20/7 1859.",
                "age": 0,
                "status": "Dánarstaður",
                "location": "Botni",
                "location_obj": {
                    "id": 25665,
                    "name": "Botn",
                    "lat": "66.151975",
                    "lng": "-18.142719",
                    "location_type": {
                        "id": 1,
                        "name": "Heimilisfang"
                    },
                    "parent": [
                        {
                            "name": "Þorgeirsfjörður",
                            "id": 25312
                        },
                        {
                            "name": "Suður-Þingeyjarsýsla",
                            "id": 1003354
                        },
                        {
                            "name": "Ísland",
                            "id": 16573
                        }
                    ]
                }
            }
        ],
        "notes": {
            "1": "Ur ellilasleika.",
            "2": "Fróður. Óg. alla ævi."
        },
        "pageUrl": "https://issuu.com/heradsskjalasafnthingeyinga/docs/b_k_42/26",
        "bok": "bok42",
        "number": 26,
        "_id": "bok42-26"
    },
    {
        "person": {
            "name": "Jónas Andrésson",
            "status": "",
            "unmarried": false,
            "birth": {
                "original_string": "F. á Silalak 5/8 1899-",
                "date": "1899-08-05",
                "location": "Silalak"
            },
            "death": {
                "original_string": "",
                "date": "",
                "location": ""
            },
            "names": [
                "Jónas",
                "Andrésson"
            ],
            "firstName": "Jónas",
            "lastName": "Andrésson"
        },
        "spouse": [
            {
                "name": "Guðrún Árnammsdóttir",
                "date": "1935-11-03",
                "status": "",
                "names": [
                    "Guðrún",
                    "Árnammsdóttir"
                ],
                "firstName": "Guðrún",
                "lastName": "Árnammsdóttir"
            }
        ],
        "spouse_original_string": "K.: Guðrún Árnammsdóttir. G. 3/11 1935",
        "parents": [
            {
                "name": "A. Jónasson",
                "note": "",
                "names": [
                    "A.",
                    "Jónasson"
                ],
                "firstName": "A.",
                "lastName": "Jónasson"
            },
            {
                "name": "Elín S. Jónasdóttir",
                "note": "",
                "names": [
                    "Elín",
                    "S.",
                    "Jónasdóttir"
                ],
                "firstName": "Elín",
                "lastName": "Jónasdóttir"
            }
        ],
        "parents_original_string": "A. Jónasson og Elín S. Jónasdóttir.",
        "residence_history": [
            {
                "year": "1899",
                "original_string": "F. á Silalak 5/8 1899-",
                "age": 0,
                "status": "Fæðingarstaður",
                "location": "Silalak"
            },
            {
                "original_string": "Hjá for. á Silalak (1. ári) 1899-1900.",
                "year": "1899-1900",
                "age": null,
                "status": "Hjá for.",
                "location": "Silalak",
                "note": "1. ári"
            }
        ],
        "notes": {},
        "pageUrl": "https://issuu.com/heradsskjalasafnthingeyinga/docs/b_k_42/27",
        "bok": "bok42",
        "number": 27,
        "_id": "bok42-27"
    }
]